Workbook
Name Aporte: 'Projeto-Controle de Investimeto'!$D$17
Name qtd_anos: 'Projeto-Controle de Investimeto'!$D$18
Name Rendimento_Carteira: 'Projeto-Controle de Investimeto'!$D$13
Name taxa_mensal: 'Projeto-Controle de Investimeto'!$D$19

Sheet Projeto-Controle de Investimeto
B11: Configurações
B12: Salário | D12: 4000
B13: Rendimento Carteira ? | D13: 0.009
B14: Sugestão de Investimento (30%) | D14: =D12*30% -> 1200
B16: Investimento Mensal
B17: Quanto investir por mês? | D17: 1200
B18: Por quantos ano? | D18: 3
B19: Taxa de rendimento mensal? | D19: 0.01079
B20: Quanto de patrimônio acumulado ? | D20: =FV(taxa_mensal,qtd_anos*12,D17*-1) -> 52450.049
B21: Dividendos mensais? | D21: =D20*$D$13 -> 472.05044
B23: Cenários | D23: Dividendos
A24: 2 | B24: Quanto em 2 anos ? | C24: =FV($D$19,$A24*12,$D$17*-1) -> 32673.153 | D24: =C24*Rendimento_Carteira -> 294.05837
A25: 5 | B25: Quanto em 5 anos ? | C25: =FV($D$19,$A25*12,$D$17*-1) -> 100532.3 | D25: =C25*Rendimento_Carteira -> 904.79067
A26: 10 | B26: Quanto em 10 anos ? | C26: =FV($D$19,$A26*12,$D$17*-1) -> 291941.06 | D26: =C26*Rendimento_Carteira -> 2627.4695
A27: 20 | B27: Quanto em 20 anos ? | C27: =FV($D$19,$A27*12,$D$17*-1) -> 1350238.1 | D27: =C27*Rendimento_Carteira -> 12152.143
A28: 30 | B28: Quanto em 30 anos ? | C28: =FV($D$19,$A28*12,$D$17*-1) -> 5186603.6 | D28: =C28*Rendimento_Carteira -> 46679.432
B31: PERFIL | C31: Conservador
B32: VALOR A SER INVESTIDO POR MÊS | C32: =Aporte -> 1200
B34: TIPO DE FII | C34: Percentual Sugerido | D34: Valores
B35: PAPEL | C35: =VLOOKUP($C$31&"-"&B35,Planilha2!$A:$D,4,FALSE) -> 0.3 | D35: =C35*$C$32 -> 360
B36: TIJOLO | C36: =VLOOKUP($C$31&"-"&B36,Planilha2!$A:$D,4,FALSE) -> 0.5 | D36: =C36*$C$32 -> 600
B37: HÍBRIDOS | C37: =VLOOKUP($C$31&"-"&B37,Planilha2!$A:$D,4,FALSE) -> 0.1 | D37: =C37*$C$32 -> 120
B38: FOF`s | C38: =VLOOKUP($C$31&"-"&B38,Planilha2!$A:$D,4,FALSE) -> 0.1 | D38: =C38*$C$32 -> 120
B39: DESENVOLVIMENTO | C39: =VLOOKUP($C$31&"-"&B39,Planilha2!$A:$D,4,FALSE) -> 0 | D39: =C39*$C$32 -> 0
B40: HOTELARIA | C40: =VLOOKUP($C$31&"-"&B40,Planilha2!$A:$D,4,FALSE) -> 0 | D40: =C40*$C$32 -> 0
D41: =SUM(D35:D40) -> 1200

Sheet Planilha2
A2: CHAVE | B2: PERFIL | C2: TIPO DE FII | D2: % | H2: %
A3: =B3&"-"&C3 -> Conservador-PAPEL | B3: Conservador | C3: PAPEL | D3: 0.3 | G3: Moderado-TIJOLO | H3: =VLOOKUP(G3,$A$2:$D$20,4,FALSE) -> 0.35
A4: =B4&"-"&C4 -> Conservador-TIJOLO | B4: Conservador | C4: TIJOLO | D4: 0.5
A5: =B5&"-"&C5 -> Conservador-HÍBRIDOS | B5: Conservador | C5: HÍBRIDOS | D5: 0.1
A6: =B6&"-"&C6 -> Conservador-FOF`s | B6: Conservador | C6: FOF`s | D6: 0.1
A7: =B7&"-"&C7 -> Conservador-DESENVOLVIMENTO | B7: Conservador | C7: DESENVOLVIMENTO | D7: 0
A8: =B8&"-"&C8 -> Conservador-HOTELARIA | B8: Conservador | C8: HOTELARIA | D8: 0
A9: =B9&"-"&C9 -> Moderado-PAPEL | B9: Moderado | C9: PAPEL | D9: 0.32
A10: =B10&"-"&C10 -> Moderado-TIJOLO | B10: Moderado | C10: TIJOLO | D10: 0.35
A11: =B11&"-"&C11 -> Moderado-HÍBRIDOS | B11: Moderado | C11: HÍBRIDOS | D11: 0.08
A12: =B12&"-"&C12 -> Moderado-FOF`s | B12: Moderado | C12: FOF`s | D12: 0.05
A13: =B13&"-"&C13 -> Moderado-DESENVOLVIMENTO | B13: Moderado | C13: DESENVOLVIMENTO | D13: 0.1
A14: =B14&"-"&C14 -> Moderado-HOTELARIA | B14: Moderado | C14: HOTELARIA | D14: 0.1
A15: =B15&"-"&C15 -> Agressivo-PAPEL | B15: Agressivo | C15: PAPEL | D15: 0.5
... A20: =B20&"-"&C20 -> Agressivo-HOTELARIA | B20: Agressivo | C20: HOTELARIA | D20: 0.1
